setup.py
rust_autoloader/__init__.py
rust_autoloader.egg-info/PKG-INFO
rust_autoloader.egg-info/SOURCES.txt
rust_autoloader.egg-info/dependency_links.txt
rust_autoloader.egg-info/not-zip-safe
rust_autoloader.egg-info/top_level.txt