Metadata-Version: 1.0
Name: rust-autoloader
Version: 0.1
Summary: An autoloader that compiles and runs rust files in your current directory
Home-page: http://github.com/bharadwaj6/rust_autoloader
Author: Bharadwaj Srigiriraju
Author-email: krishna.bharadwaj6@gmail.com
License: MIT
Platform: UNKNOWN
